scale2pdf/__init__.py
scale2pdf/extractpdfimage.py
scale2pdf/pdfparse.py
scale2pdf/scalepdfray.py
scale2pdf-0.0.7.dist-info/METADATA
scale2pdf-0.0.7.dist-info/WHEEL
scale2pdf-0.0.7.dist-info/top_level.txt
scale2pdf-0.0.7.dist-info/RECORD
