Metadata-Version: 2.1
Name: scale2pdf
Version: 0.0.7
Author: ammar
Author-email: sleeping4cat@outlook.com
Requires-Dist: PyMuPDF
Requires-Dist: Pillow
Requires-Dist: papermage[dev,predictors,visualizers]
